django_loci/__init__.py
django_loci/admin.py
django_loci/apps.py
django_loci/fields.py
django_loci/models.py
django_loci/settings.py
django_loci/storage.py
django_loci/widgets.py
django_loci/base/__init__.py
django_loci/base/admin.py
django_loci/base/geocoding_views.py
django_loci/base/models.py
django_loci/channels/__init__.py
django_loci/channels/asgi.py
django_loci/channels/base.py
django_loci/channels/consumers.py
django_loci/channels/receivers.py
django_loci/migrations/0001_initial.py
django_loci/migrations/__init__.py
django_loci/static/django-loci/css/floorplan-widget.css
django_loci/static/django-loci/css/loci.css
django_loci/static/django-loci/js/floorplan-inlines.js
django_loci/static/django-loci/js/floorplan-widget.js
django_loci/static/django-loci/js/loci.js
django_loci/static/django-loci/js/vendor/reconnecting-websocket.min.js
django_loci/templates/admin/django_loci/foreign_key_raw_id.html
django_loci/templates/admin/django_loci/location_change_form.html
django_loci/templates/admin/django_loci/location_inline.html
django_loci/templates/admin/widgets/floorplan.html
django_loci/templates/admin/widgets/foreign_key_raw_id.html
django_loci/templates/admin/widgets/image.html
django_loci/tests/__init__.py
django_loci/tests/pytest_channels.py
django_loci/tests/test_admin.py
django_loci/tests/test_admin_inline.py
django_loci/tests/test_apps.py
django_loci/tests/test_models.py
django_loci/tests/test_selenium.py
django_loci/tests/base/__init__.py
django_loci/tests/base/test_admin.py
django_loci/tests/base/test_admin_inline.py
django_loci/tests/base/test_apps.py
django_loci/tests/base/test_channels.py
django_loci/tests/base/test_models.py
django_loci/tests/base/test_selenium.py
django_loci/tests/base/static/test-geocode-invalid-address.json
django_loci/tests/base/static/test-geocode.json
django_loci/tests/base/static/test-reverse-geocode.json
django_loci/tests/base/static/test-reverse-location-with-no-address.json
django_loci/tests/testdeviceapp/__init__.py
django_loci-1.2.dist-info/licenses/LICENSE
django_loci-1.2.dist-info/METADATA
django_loci-1.2.dist-info/WHEEL
django_loci-1.2.dist-info/top_level.txt
django_loci-1.2.dist-info/RECORD
