Metadata-Version: 2.4
Name: django-loci
Version: 1.2
Summary: Reusable django-app for outdoor and indoor mapping
Home-page: http://openwisp.org
Download-URL: https://github.com/openwisp/django-loci/releases
Author: Federico Capoano
Author-email: support@openwisp.io
License: BSD
Keywords: django,gis
Platform: Platform Independent
Classifier: Development Status :: 5 - Production/Stable
Classifier: Environment :: Web Environment
Classifier: Topic :: Internet :: WWW/HTTP
Classifier: Topic :: Scientific/Engineering :: GIS
Classifier: Intended Audience :: Developers
Classifier: License :: OSI Approved :: BSD License
Classifier: Operating System :: OS Independent
Classifier: Framework :: Django
Classifier: Programming Language :: Python :: 3
License-File: LICENSE
Requires-Dist: django<5.3.0,>=4.2.0
Requires-Dist: django-leaflet~=0.32.0
Requires-Dist: Pillow~=11.3.0
Requires-Dist: geopy~=2.4.1
Requires-Dist: openwisp-utils[channels]~=1.2.0
Dynamic: author
Dynamic: author-email
Dynamic: classifier
Dynamic: description
Dynamic: download-url
Dynamic: home-page
Dynamic: keywords
Dynamic: license
Dynamic: license-file
Dynamic: platform
Dynamic: requires-dist
Dynamic: summary
